pytorch_logit_logic/__init__.py
pytorch_logit_logic/__meta__.py
pytorch_logit_logic/actfuns.py
pytorch_logit_logic-1.0.0.dist-info/LICENSE
pytorch_logit_logic-1.0.0.dist-info/METADATA
pytorch_logit_logic-1.0.0.dist-info/WHEEL
pytorch_logit_logic-1.0.0.dist-info/top_level.txt
pytorch_logit_logic-1.0.0.dist-info/RECORD
